aiop4/__init__.py
aiop4/client.py
aiop4/elems_info.py
aiop4/exceptions.py
aiop4/utils.py
aiop4-0.4.1.dist-info/LICENSE
aiop4-0.4.1.dist-info/METADATA
aiop4-0.4.1.dist-info/WHEEL
aiop4-0.4.1.dist-info/RECORD
