Metadata-Version: 2.3
Name: aiop4
Version: 0.4.1
Summary: asyncio P4Runtime Python client
License: Apache-2.0
Keywords: p4,p4runtime,p4runtime-client,client,aiop4
Author: Vinicius Arcanjo
Author-email: viniarck@gmail.com
Requires-Python: >=3.11,<4.0
Classifier: License :: OSI Approved :: Apache Software License
Classifier: Programming Language :: Python :: 3
Classifier: Programming Language :: Python :: 3.11
Classifier: Programming Language :: Python :: 3.12
Classifier: Programming Language :: Python :: 3.13
Requires-Dist: googleapis-common-protos (==1.54.0)
Requires-Dist: grpcio (==1.51.3)
Requires-Dist: p4runtime (==1.4.1)
Requires-Dist: protobuf (==3.20.3)
Project-URL: Repository, https://github.com/viniarck/aiop4
